syntax_checker-0.4.0.dist-info/METADATA
syntax_checker-0.4.0.dist-info/WHEEL
syntax_checker-0.4.0.dist-info/licenses/LICENSE
syntax_checker/__init__.py
syntax_checker/__init__.pyi
syntax_checker/py.typed
syntax_checker/syntax_checker.cpython-310-i386-linux-gnu.so
syntax_checker-0.4.0.dist-info/RECORD
