Metadata-Version: 2.4
Name: syntax-checker
Version: 0.4.0
Classifier: Programming Language :: Python :: 3
Classifier: Programming Language :: Python :: 3.7
Classifier: Programming Language :: Python :: 3.8
Classifier: Programming Language :: Python :: 3.9
Classifier: Programming Language :: Python :: 3.10
Classifier: Programming Language :: Python :: 3.11
Classifier: Programming Language :: Rust
Classifier: Topic :: Software Development :: Libraries :: Python Modules
Classifier: Topic :: Text Processing :: General
License-File: LICENSE
Summary: A syntax checker for multiple languages using tree-sitter
Home-Page: https://github.com/rusiaaman/syntax-checker
Author-email: Aman Rusia <gapypi@arcfu.com>
Requires-Python: >=3.7
Project-URL: Source Code, https://github.com/rusiaaman/syntax-checker
